<?xml version="1.0" encoding="UTF-8"?>
<brandOrderStatusNotifications xmlns="http://api.anatwine.com/schemas/brand/v3/notifications">
	<notifications>
		<notification>
			<orderNotificationCreated>2017-03-12T12:00:00</orderNotificationCreated>
			<orderNotificationId>0123456789</orderNotificationId>
			<anatwineOrderId>30080043</anatwineOrderId>
			<orderLines>
				<orderLine>
					<OrderLineId>001</OrderLineId>
					<notificationType>AWAITING_FULFILMENT</notificationType>
					<quantity>1</quantity>
					<trackingReference/>			 
				</orderLine>
				<orderLine>  
					<OrderLineId>002</OrderLineId>               
					<notificationType>AWAITING_FULFILMENT</notificationType>
					<quantity>1</quantity> 
					<trackingReference/>
				</orderLine>
			</orderLines>
		</notification>
		<notification>
			<orderNotificationCreated>2017-03-12T12:00:00</orderNotificationCreated>
			<orderNotificationId>0987654322</orderNotificationId>
			<anatwineOrderId>30080087</anatwineOrderId>
			<orderLines>
				<orderLine>
					<OrderLineId>001</OrderLineId>
					<notificationType>CANCELLED</notificationType> 
					<quantity>1</quantity>             
					<reasonCode>NO_INV</reasonCode> 
					<trackingReference/>
				</orderLine>
				<orderLine>  
					<OrderLineId>002</OrderLineId>               
					<notificationType>SHIPPED</notificationType>
					<quantity>1</quantity>              
					<trackingReference>JK1234567890123</trackingReference>
				</orderLine>
			</orderLines>
		</notification>
		<notification>
			<orderNotificationCreated>2017-03-12T12:00:00</orderNotificationCreated>
			<orderNotificationId>0982563725</orderNotificationId>
			<anatwineOrderId>300800109</anatwineOrderId>
			<orderLines>
				<orderLine>
					<OrderLineId>001</OrderLineId>
					<notificationType>RETURNED</notificationType>
					<quantity>1</quantity>               
					<reasonCode>ITEM_TOO_BIG</reasonCode> 
					<trackingReference/>
					<returnTrackingReference>JW1234567890123</returnTrackingReference>
				</orderLine>
			</orderLines>
		</notification>
	</notifications>
</brandOrderStatusNotifications>